strawberry_azure_auth/__init__.py
strawberry_azure_auth/channels/__init__.py
strawberry_azure_auth/channels/context.py
strawberry_azure_auth/channels/handlers.py
strawberry_azure_auth/channels/schema.py
strawberry_azure_auth/django/__init__.py
strawberry_azure_auth/django/context.py
strawberry_azure_auth/extension.py
strawberry_azure_auth/openid.py
strawberry_azure_auth/permissions.py
strawberry_azure_auth/types.py
strawberry_azure_auth/utils.py
strawberry_azure_auth-2.1.0.dist-info/LICENSE
strawberry_azure_auth-2.1.0.dist-info/METADATA
strawberry_azure_auth-2.1.0.dist-info/WHEEL
strawberry_azure_auth-2.1.0.dist-info/RECORD
