Metadata-Version: 2.1
Name: strawberry-azure-auth
Version: 2.1.0
Summary: Azure AD authentication for Strawberry GraphQL
Home-page: https://github.com/skarre-r/strawberry-azure-auth
License: MIT
Author: skarre-r
Author-email: skarre-r@protonmail.com
Requires-Python: >=3.11,<4.0
Classifier: License :: OSI Approved :: MIT License
Classifier: Programming Language :: Python :: 3
Classifier: Programming Language :: Python :: 3.11
Requires-Dist: httpx (>=0.24.1,<0.25.0)
Requires-Dist: pyjwt[crypto] (>=2.7.0,<3.0.0)
Requires-Dist: strawberry-graphql-django (>=0.10.2)
Requires-Dist: strawberry-graphql[channels] (>=0.193.1)
Project-URL: Repository, https://github.com/skarre-r/strawberry-azure-auth
